NumpyZhongwenWendang11120170215/README.md
NumpyZhongwenWendang11120170215/__init__.py
NumpyZhongwenWendang11120170215/__main__.py
NumpyZhongwenWendang11120170215/file.epub
NumpyZhongwenWendang11120170215/index.html
NumpyZhongwenWendang11120170215/css/__init__.py
NumpyZhongwenWendang11120170215/css/annotations.css
NumpyZhongwenWendang11120170215/css/main.css
NumpyZhongwenWendang11120170215/css/normalize.css
NumpyZhongwenWendang11120170215/css/popup.css
NumpyZhongwenWendang11120170215/font/__init__.py
NumpyZhongwenWendang11120170215/font/fontello.eot
NumpyZhongwenWendang11120170215/font/fontello.svg
NumpyZhongwenWendang11120170215/font/fontello.ttf
NumpyZhongwenWendang11120170215/font/fontello.woff
NumpyZhongwenWendang11120170215/img/__init__.py
NumpyZhongwenWendang11120170215/img/annotator-glyph-sprite.png
NumpyZhongwenWendang11120170215/img/annotator-icon-sprite.png
NumpyZhongwenWendang11120170215/img/apple-touch-icon.png
NumpyZhongwenWendang11120170215/img/cancelfullscreen.png
NumpyZhongwenWendang11120170215/img/close.png
NumpyZhongwenWendang11120170215/img/fullscreen.png
NumpyZhongwenWendang11120170215/img/loader.gif
NumpyZhongwenWendang11120170215/img/menu-icon.png
NumpyZhongwenWendang11120170215/img/save.png
NumpyZhongwenWendang11120170215/img/saved.png
NumpyZhongwenWendang11120170215/img/settings-s.png
NumpyZhongwenWendang11120170215/img/settings.png
NumpyZhongwenWendang11120170215/img/star.png
NumpyZhongwenWendang11120170215/js/__init__.py
NumpyZhongwenWendang11120170215/js/epub.js
NumpyZhongwenWendang11120170215/js/epub.min.js
NumpyZhongwenWendang11120170215/js/epub.min.map
NumpyZhongwenWendang11120170215/js/hooks.min.js
NumpyZhongwenWendang11120170215/js/hooks.min.map
NumpyZhongwenWendang11120170215/js/reader.js
NumpyZhongwenWendang11120170215/js/reader.js.map
NumpyZhongwenWendang11120170215/js/reader.min.js
NumpyZhongwenWendang11120170215/js/reader.min.map
NumpyZhongwenWendang11120170215/js/hooks/__init__.py
numpy_zhongwen_wendang_1_11_20170215-2024.3.2.0.dist-info/METADATA
numpy_zhongwen_wendang_1_11_20170215-2024.3.2.0.dist-info/WHEEL
numpy_zhongwen_wendang_1_11_20170215-2024.3.2.0.dist-info/entry_points.txt
numpy_zhongwen_wendang_1_11_20170215-2024.3.2.0.dist-info/top_level.txt
numpy_zhongwen_wendang_1_11_20170215-2024.3.2.0.dist-info/RECORD
